django_dataclass_autoserialize/__init__.py
django_dataclass_autoserialize/__version__.py
django_dataclass_autoserialize/py.typed
django_dataclass_autoserialize/settings_test.py
django_dataclass_autoserialize-1.0.1.dist-info/METADATA
django_dataclass_autoserialize-1.0.1.dist-info/WHEEL
django_dataclass_autoserialize-1.0.1.dist-info/top_level.txt
django_dataclass_autoserialize-1.0.1.dist-info/RECORD
