Metadata-Version: 2.1
Name: django-dataclass-autoserialize
Version: 1.0.1
Summary: UNKNOWN
Home-page: https://github.com/thegangtechnology/django-dataclass-autoserialize
Author: Piti Ongmongkolkul
Author-email: o.piti@thegang.tech
License: BSD
Platform: UNKNOWN
Classifier: 
Requires-Dist: djangorestframework-dataclasses
Requires-Dist: drf-yasg
Provides-Extra: dev
Requires-Dist: mypy ; extra == 'dev'
Requires-Dist: autopep8 ; extra == 'dev'
Requires-Dist: pytest ; extra == 'dev'
Requires-Dist: pytest-cov ; extra == 'dev'
